sunpy/CITATION.rst
sunpy/__init__.py
sunpy/_version.py
sunpy/conftest.py
sunpy/version.py
sunpy/coordinates/__init__.py
sunpy/coordinates/_transformations.py
sunpy/coordinates/ephemeris.py
sunpy/coordinates/frameattributes.py
sunpy/coordinates/frames.py
sunpy/coordinates/metaframes.py
sunpy/coordinates/offset_frame.py
sunpy/coordinates/screens.py
sunpy/coordinates/spice.py
sunpy/coordinates/sun.py
sunpy/coordinates/utils.py
sunpy/coordinates/wcs_utils.py
sunpy/coordinates/data/igrf13coeffs.txt
sunpy/coordinates/tests/__init__.py
sunpy/coordinates/tests/conftest.py
sunpy/coordinates/tests/helpers.py
sunpy/coordinates/tests/strategies.py
sunpy/coordinates/tests/test_ephemeris.py
sunpy/coordinates/tests/test_frameattributes.py
sunpy/coordinates/tests/test_frames.py
sunpy/coordinates/tests/test_metaframes.py
sunpy/coordinates/tests/test_offset_frame.py
sunpy/coordinates/tests/test_spice.py
sunpy/coordinates/tests/test_sun.py
sunpy/coordinates/tests/test_transformations.py
sunpy/coordinates/tests/test_utils.py
sunpy/coordinates/tests/test_wcs_utils.py
sunpy/data/README.rst
sunpy/data/The_Blue_Marble_150px.png
sunpy/data/__init__.py
sunpy/data/_sample.py
sunpy/data/sample.py
sunpy/data/sunpyrc
sunpy/data/data_manager/__init__.py
sunpy/data/data_manager/cache.py
sunpy/data/data_manager/downloader.py
sunpy/data/data_manager/manager.py
sunpy/data/data_manager/storage.py
sunpy/data/data_manager/tests/__init__.py
sunpy/data/data_manager/tests/conftest.py
sunpy/data/data_manager/tests/db_testdata.csv
sunpy/data/data_manager/tests/mocks.py
sunpy/data/data_manager/tests/test_cache.py
sunpy/data/data_manager/tests/test_downloader.py
sunpy/data/data_manager/tests/test_manager.py
sunpy/data/data_manager/tests/test_storage.py
sunpy/data/test/2013_05_13__16_54_06_137__SOHO_LASCO_C3_white-light.jp2
sunpy/data/test/2013_06_24__17_31_30_84__SDO_AIA_AIA_193.jp2
sunpy/data/test/20181209_180305_kcor_l2.header
sunpy/data/test/2022_04_01__00_00_45__SOLO-EUI-FSI_EUI_FSI_174.jp2
sunpy-7.1.0.dist-info/licenses/LICENSE.rst
sunpy-7.1.0.dist-info/licenses/licenses/ASTROPY.rst
sunpy-7.1.0.dist-info/licenses/licenses/GLUE.rst
sunpy-7.1.0.dist-info/licenses/licenses/README.rst
sunpy-7.1.0.dist-info/licenses/licenses/TOWNCRIER.rst
sunpy-7.1.0.dist-info/METADATA
sunpy-7.1.0.dist-info/WHEEL
sunpy-7.1.0.dist-info/entry_points.txt
sunpy-7.1.0.dist-info/top_level.txt
sunpy-7.1.0.dist-info/RECORD
