Metadata-Version: 2.4
Name: sunpy
Version: 7.1.0
Summary: SunPy core package: Python for Solar Physics
Author-email: The SunPy Community <sunpy@googlegroups.com>
License-Expression: BSD-3-Clause
Project-URL: Homepage, https://sunpy.org
Project-URL: Source Code, https://github.com/sunpy/sunpy
Project-URL: Download, https://pypi.org/project/sunpy
Project-URL: Documentation, https://docs.sunpy.org
Project-URL: Changelog, https://docs.sunpy.org/en/stable/whatsnew/changelog.html
Project-URL: Issue Tracker, https://github.com/sunpy/sunpy/issues
Keywords: solar physics,solar,science,sun,wcs,coordinates
Platform: any
Classifier: Development Status :: 5 - Production/Stable
Classifier: Intended Audience :: Science/Research
Classifier: Natural Language :: English
Classifier: Operating System :: OS Independent
Classifier: Programming Language :: Python
Classifier: Programming Language :: Python :: 3
Classifier: Programming Language :: Python :: 3.11
Classifier: Programming Language :: Python :: 3.12
Classifier: Programming Language :: Python :: 3.13
Classifier: Programming Language :: Python :: 3.14
Classifier: Topic :: Scientific/Engineering :: Physics
Provides: sunpy
Requires-Python: >=3.12
License-File: LICENSE.rst
License-File: licenses/ASTROPY.rst
License-File: licenses/GLUE.rst
License-File: licenses/README.rst
License-File: licenses/TOWNCRIER.rst
Requires-Dist: astropy>=6.1.0
Requires-Dist: fsspec>=2023.6.0
Requires-Dist: numpy>=1.26.0
Requires-Dist: numpy>=2.3.0; python_version == "3.14"
Requires-Dist: packaging>=23.2
Requires-Dist: parfive[ftp]>=2.1.0
Requires-Dist: pyerfa>=2.0.1.1
Requires-Dist: requests>=2.32.1
Provides-Extra: asdf
Requires-Dist: asdf-astropy>=0.5.0; extra == "asdf"
Requires-Dist: asdf>=3.0.0; extra == "asdf"
Provides-Extra: dask
Requires-Dist: dask[array]>=2023.6.0; extra == "dask"
Provides-Extra: image
Requires-Dist: scipy>=1.12.0; extra == "image"
Provides-Extra: jpeg2000
Requires-Dist: glymur>=0.13.0; extra == "jpeg2000"
Requires-Dist: lxml>=5.0.1; extra == "jpeg2000"
Provides-Extra: map
Requires-Dist: contourpy>=1.1.0; extra == "map"
Requires-Dist: matplotlib>=3.8.0; extra == "map"
Requires-Dist: mpl-animators>=1.2.0; extra == "map"
Requires-Dist: reproject>=0.13.0; extra == "map"
Requires-Dist: scipy>=1.12.0; extra == "map"
Provides-Extra: opencv
Requires-Dist: opencv-python>=4.8.0.74; extra == "opencv"
Provides-Extra: net
Requires-Dist: beautifulsoup4>=4.13.1; extra == "net"
Requires-Dist: drms>=0.7.1; extra == "net"
Requires-Dist: python-dateutil>=2.9.0; extra == "net"
Requires-Dist: tqdm>=4.66.0; extra == "net"
Requires-Dist: zeep>=4.3.0; extra == "net"
Provides-Extra: scikit-image
Requires-Dist: scikit-image>=0.21.0; extra == "scikit-image"
Provides-Extra: spice
Requires-Dist: spiceypy>=6.0.0; extra == "spice"
Provides-Extra: timeseries
Requires-Dist: cdflib>=1.3.2; extra == "timeseries"
Requires-Dist: h5netcdf>=1.2.0; extra == "timeseries"
Requires-Dist: h5py>=3.10.0; extra == "timeseries"
Requires-Dist: matplotlib>=3.8.0; extra == "timeseries"
Requires-Dist: pandas>=2.2.0; extra == "timeseries"
Provides-Extra: visualization
Requires-Dist: matplotlib>=3.8.0; extra == "visualization"
Requires-Dist: mpl-animators>=1.2.0; extra == "visualization"
Provides-Extra: core
Requires-Dist: sunpy[image,map,net,timeseries,visualization]; extra == "core"
Provides-Extra: all
Requires-Dist: sunpy[asdf,core,jpeg2000,opencv,scikit-image,spice]; extra == "all"
Provides-Extra: s3
Requires-Dist: fsspec[s3]>=2023.6.0; extra == "s3"
Requires-Dist: aiobotocore[boto3]>=2.6.0; extra == "s3"
Provides-Extra: jupyter
Requires-Dist: itables>=2.2.4; extra == "jupyter"
Requires-Dist: ipywidgets>=8.1.0; extra == "jupyter"
Provides-Extra: tests-only
Requires-Dist: hvpy>=1.1.0; extra == "tests-only"
Requires-Dist: jplephem>=2.19; extra == "tests-only"
Requires-Dist: pytest-astropy>=0.11.0; extra == "tests-only"
Requires-Dist: pytest-mpl>=0.18.0; extra == "tests-only"
Requires-Dist: pytest>=7.4.0; extra == "tests-only"
Provides-Extra: asdf-tests
Requires-Dist: sunpy[asdf]; extra == "asdf-tests"
Requires-Dist: pytest-asdf-plugin>=0.1.1; extra == "asdf-tests"
Provides-Extra: tests
Requires-Dist: sunpy[all,asdf-tests,jupyter,s3,tests-only]; extra == "tests"
Provides-Extra: docs
Requires-Dist: sunpy[all]; extra == "docs"
Requires-Dist: sphinx>=7.1.0; extra == "docs"
Requires-Dist: sphinx-automodapi>=0.16.0; extra == "docs"
Requires-Dist: packaging>=23.2; extra == "docs"
Requires-Dist: hvpy>=1.1.0; extra == "docs"
Requires-Dist: ruamel.yaml>=0.18.0; extra == "docs"
Requires-Dist: sphinx-changelog>=1.5.0; extra == "docs"
Requires-Dist: sphinx-copybutton>=0.5.0; extra == "docs"
Requires-Dist: sphinx-design>=0.5.0; extra == "docs"
Requires-Dist: sphinx-gallery>=0.14.0; extra == "docs"
Requires-Dist: sphinxext-opengraph>=0.9.0; extra == "docs"
Requires-Dist: sunpy-sphinx-theme>=2.0.3; extra == "docs"
Requires-Dist: sphinxcontrib-bibtex; extra == "docs"
Requires-Dist: joblib; extra == "docs"
Provides-Extra: docs-gallery
Requires-Dist: sunpy[docs]; extra == "docs-gallery"
Requires-Dist: astroquery>=0.4.6; extra == "docs-gallery"
Requires-Dist: jplephem>=2.19; extra == "docs-gallery"
Requires-Dist: pillow; extra == "docs-gallery"
Provides-Extra: dev
Requires-Dist: sunpy[docs,tests]; extra == "dev"
Dynamic: license-file
